ververser/__init__.py
ververser/content_manager.py
ververser/entrypoint_wrapper.py
ververser/examples/1_minimal_setup/README.md
ververser/examples/1_minimal_setup/vvs_main.py
ververser/examples/2_host_separate_folder/__main__.py
ververser/examples/2_host_separate_folder/content/vvs_main.py
ververser/examples/2_host_separate_folder/README.md
ververser/examples/3_game_class/README.md
ververser/examples/3_game_class/vvs_game.py
ververser/examples/4_local_reinitialisation/color_for_time.py
ververser/examples/4_local_reinitialisation/README.md
ververser/examples/4_local_reinitialisation/vvs_game.py
ververser/examples/5_mouse_and_keyboard/README.md
ververser/examples/5_mouse_and_keyboard/vvs_game.py
ververser/file_watcher.py
ververser/fps_counter.py
ververser/game_stepper.py
ververser/game_window.py
ververser/global_game_window.py
ververser/host_this_folder.py
ververser/import_script.py
ververser/keyboard.py
ververser/mouse.py
ververser/multi_file_watcher.py
ververser/reloading_asset.py
ververser/script.py
ververser/timer.py
ververser-0.1.26.dist-info/WHEEL
ververser-0.1.26.dist-info/METADATA
ververser-0.1.26.dist-info/RECORD
