Metadata-Version: 2.1
Name: ververser
Version: 0.1.26
Summary: A lightweight wrapper around pyglet that allows hot-reloading of content.
Author: Berry van Someren
Requires-Python: >=3.10,<4.0
Classifier: Programming Language :: Python :: 3
Classifier: Programming Language :: Python :: 3.10
Classifier: Programming Language :: Python :: 3.11
Requires-Dist: numpy (>=1.24.2,<2.0.0)
Requires-Dist: pyglet (>=2.0.5,<3.0.0)
